{
    "1973-11-01": {
        "open": null,
        "high": null,
        "low": null,
        "close": 4634.83
    },
    "1973-11-02": {
        "open": null,
        "high": null,
        "low": null,
        "close": 4665.98
    },
    "1973-11-05": {
        "open": null,
        "high": null,
        "low": null,
        "close": 4676.96
    },
    "1973-11-06": {
        "open": null,
        "high": null,
        "low": null,
        "close": 4616.62
    },
    "1973-11-07": {
        "open": null,
        "high": null,
        "low": null,
        "close": 4632.43
    },
    "1973-11-08": {
        "open": null,
        "high": null,
        "low": null,
        "close": 4660.66
    },
    "1973-11-09": {
        "open": null,
        "high": null,
        "low": null,
        "close": 4649
    },
    "1973-11-10": {
        "open": null,
        "high": null,
        "low": null,
        "close": 4595.27
    },
    "1973-11-12": {
        "open": null,
        "high": null,
        "low": null,
        "close": 4510.32
    },
    "1973-11-13": {
        "open": null,
        "high": null,
        "low": null,
        "close": 4428.39
    },
    "1973-11-14": {
        "open": null,
        "high": null,
        "low": null,
        "close": 4473.75
    },
    "1973-11-15": {
        "open": null,
        "high": null,
        "low": null,
        "close": 4444.87
    },
    "1973-11-16": {
        "open": null,
        "high": null,
        "low": null,
        "close": 4388.1
    },
    "1973-11-19": {
        "open": null,
        "high": null,
        "low": null,
        "close": 4450.89
    },
    "1973-11-20": {
        "open": null,
        "high": null,
        "low": null,
        "close": 4441.89
    },
    "1973-11-21": {
        "open": null,
        "high": null,
        "low": null,
        "close": 4371.55
    },
    "1973-11-22": {
        "open": null,
        "high": null,
        "low": null,
        "close": 4293.5
    },
    "1973-11-24": {
        "open": null,
        "high": null,
        "low": null,
        "close": 4332.96
    },
    "1973-11-26": {
        "open": null,
        "high": null,
        "low": null,
        "close": 4371.71
    },
    "1973-11-27": {
        "open": null,
        "high": null,
        "low": null,
        "close": 4288.75
    },
    "1973-11-28": {
        "open": null,
        "high": null,
        "low": null,
        "close": 4352.68
    },
    "1973-11-29": {
        "open": null,
        "high": null,
        "low": null,
        "close": 4411.44
    },
    "1973-11-30": {
        "open": null,
        "high": null,
        "low": null,
        "close": 4461.84
    }
}
