{
    "1976-07-01": {
        "open": null,
        "high": null,
        "low": null,
        "close": 4865.55
    },
    "1976-07-02": {
        "open": null,
        "high": null,
        "low": null,
        "close": 4853.68
    },
    "1976-07-03": {
        "open": null,
        "high": null,
        "low": null,
        "close": 4853.23
    },
    "1976-07-05": {
        "open": null,
        "high": null,
        "low": null,
        "close": 4846.5
    },
    "1976-07-06": {
        "open": null,
        "high": null,
        "low": null,
        "close": 4843.28
    },
    "1976-07-07": {
        "open": null,
        "high": null,
        "low": null,
        "close": 4854.54
    },
    "1976-07-08": {
        "open": null,
        "high": null,
        "low": null,
        "close": 4814.17
    },
    "1976-07-09": {
        "open": null,
        "high": null,
        "low": null,
        "close": 4839
    },
    "1976-07-10": {
        "open": null,
        "high": null,
        "low": null,
        "close": 4844.25
    },
    "1976-07-12": {
        "open": null,
        "high": null,
        "low": null,
        "close": 4808.03
    },
    "1976-07-13": {
        "open": null,
        "high": null,
        "low": null,
        "close": 4775.4
    },
    "1976-07-14": {
        "open": null,
        "high": null,
        "low": null,
        "close": 4746.39
    },
    "1976-07-15": {
        "open": null,
        "high": null,
        "low": null,
        "close": 4695.68
    },
    "1976-07-16": {
        "open": null,
        "high": null,
        "low": null,
        "close": 4708.48
    },
    "1976-07-19": {
        "open": null,
        "high": null,
        "low": null,
        "close": 4688.49
    },
    "1976-07-20": {
        "open": null,
        "high": null,
        "low": null,
        "close": 4706.81
    },
    "1976-07-21": {
        "open": null,
        "high": null,
        "low": null,
        "close": 4697.09
    },
    "1976-07-22": {
        "open": null,
        "high": null,
        "low": null,
        "close": 4705.24
    },
    "1976-07-23": {
        "open": null,
        "high": null,
        "low": null,
        "close": 4721.48
    },
    "1976-07-24": {
        "open": null,
        "high": null,
        "low": null,
        "close": 4705.57
    },
    "1976-07-26": {
        "open": null,
        "high": null,
        "low": null,
        "close": 4667.1
    },
    "1976-07-27": {
        "open": null,
        "high": null,
        "low": null,
        "close": 4679.51
    },
    "1976-07-28": {
        "open": null,
        "high": null,
        "low": null,
        "close": 4678.22
    },
    "1976-07-29": {
        "open": null,
        "high": null,
        "low": null,
        "close": 4646.6
    },
    "1976-07-30": {
        "open": null,
        "high": null,
        "low": null,
        "close": 4641.83
    },
    "1976-07-31": {
        "open": null,
        "high": null,
        "low": null,
        "close": 4655.78
    }
}
