{
    "1977-04-01": {
        "open": null,
        "high": null,
        "low": null,
        "close": 5001.21
    },
    "1977-04-02": {
        "open": null,
        "high": null,
        "low": null,
        "close": 4984.78
    },
    "1977-04-04": {
        "open": null,
        "high": null,
        "low": null,
        "close": 4970.68
    },
    "1977-04-05": {
        "open": null,
        "high": null,
        "low": null,
        "close": 4879.53
    },
    "1977-04-06": {
        "open": null,
        "high": null,
        "low": null,
        "close": 4893.32
    },
    "1977-04-07": {
        "open": null,
        "high": null,
        "low": null,
        "close": 4870.24
    },
    "1977-04-08": {
        "open": null,
        "high": null,
        "low": null,
        "close": 4890.21
    },
    "1977-04-09": {
        "open": null,
        "high": null,
        "low": null,
        "close": 4928.03
    },
    "1977-04-11": {
        "open": null,
        "high": null,
        "low": null,
        "close": 4926.56
    },
    "1977-04-12": {
        "open": null,
        "high": null,
        "low": null,
        "close": 4969
    },
    "1977-04-13": {
        "open": null,
        "high": null,
        "low": null,
        "close": 5011.6
    },
    "1977-04-14": {
        "open": null,
        "high": null,
        "low": null,
        "close": 5021.13
    },
    "1977-04-15": {
        "open": null,
        "high": null,
        "low": null,
        "close": 5037.73
    },
    "1977-04-18": {
        "open": null,
        "high": null,
        "low": null,
        "close": 5034.77
    },
    "1977-04-19": {
        "open": null,
        "high": null,
        "low": null,
        "close": 5075.43
    },
    "1977-04-20": {
        "open": null,
        "high": null,
        "low": null,
        "close": 5118.44
    },
    "1977-04-21": {
        "open": null,
        "high": null,
        "low": null,
        "close": 5157.07
    },
    "1977-04-22": {
        "open": null,
        "high": null,
        "low": null,
        "close": 5143.32
    },
    "1977-04-23": {
        "open": null,
        "high": null,
        "low": null,
        "close": 5135.02
    },
    "1977-04-25": {
        "open": null,
        "high": null,
        "low": null,
        "close": 5102.9
    },
    "1977-04-26": {
        "open": null,
        "high": null,
        "low": null,
        "close": 5092.9
    },
    "1977-04-27": {
        "open": null,
        "high": null,
        "low": null,
        "close": 5091.96
    },
    "1977-04-28": {
        "open": null,
        "high": null,
        "low": null,
        "close": 5099.05
    },
    "1977-04-30": {
        "open": null,
        "high": null,
        "low": null,
        "close": 5102.39
    }
}
