{
    "1985-10-01": {
        "open": 12705.37,
        "high": 12731.4,
        "low": 12674.56,
        "close": 12685.36
    },
    "1985-10-02": {
        "open": 12683.77,
        "high": 12751.5,
        "low": 12683.67,
        "close": 12720.5
    },
    "1985-10-03": {
        "open": 12715.8,
        "high": 12726.04,
        "low": 12683.2,
        "close": 12700.86
    },
    "1985-10-04": {
        "open": 12698.23,
        "high": 12723.51,
        "low": 12685.64,
        "close": 12713.83
    },
    "1985-10-05": {
        "open": 12701.9,
        "high": 12751.5,
        "low": 12701.9,
        "close": 12750.66
    },
    "1985-10-07": {
        "open": 12753.57,
        "high": 12803.27,
        "low": 12753.57,
        "close": 12792
    },
    "1985-10-08": {
        "open": 12794.81,
        "high": 12844.04,
        "low": 12794.25,
        "close": 12835.21
    },
    "1985-10-09": {
        "open": 12845.17,
        "high": 12882.66,
        "low": 12843.48,
        "close": 12857.2
    },
    "1985-10-11": {
        "open": 12856.82,
        "high": 12951.8,
        "low": 12856.82,
        "close": 12949.92
    },
    "1985-10-14": {
        "open": 12955.37,
        "high": 13018.98,
        "low": 12955.37,
        "close": 13017.29
    },
    "1985-10-15": {
        "open": 13021.7,
        "high": 13056.37,
        "low": 13014.28,
        "close": 13055.52
    },
    "1985-10-16": {
        "open": 13048.59,
        "high": 13079.03,
        "low": 13022.65,
        "close": 13036.56
    },
    "1985-10-17": {
        "open": 13038.62,
        "high": 13049.24,
        "low": 12974.81,
        "close": 13021.14
    },
    "1985-10-18": {
        "open": 13018.8,
        "high": 13050.47,
        "low": 12969.74,
        "close": 12973.22
    },
    "1985-10-19": {
        "open": 12969.93,
        "high": 13016.54,
        "low": 12965.79,
        "close": 13015.69
    },
    "1985-10-21": {
        "open": 13019.36,
        "high": 13049.9,
        "low": 13008.83,
        "close": 13023.21
    },
    "1985-10-22": {
        "open": 13021.05,
        "high": 13044.26,
        "low": 12999.62,
        "close": 13001.69
    },
    "1985-10-23": {
        "open": 13005.26,
        "high": 13033.27,
        "low": 12945.59,
        "close": 12946.53
    },
    "1985-10-24": {
        "open": 12937.69,
        "high": 12969.08,
        "low": 12857.72,
        "close": 12969.08
    },
    "1985-10-25": {
        "open": 12988.35,
        "high": 13063.53,
        "low": 12841.18,
        "close": 12854.99
    },
    "1985-10-26": {
        "open": 12839.86,
        "high": 12839.86,
        "low": 12710.46,
        "close": 12832.63
    },
    "1985-10-28": {
        "open": 12843.06,
        "high": 12987.41,
        "low": 12843.06,
        "close": 12937.04
    },
    "1985-10-29": {
        "open": 12930.93,
        "high": 12973.31,
        "low": 12885.91,
        "close": 12913.92
    },
    "1985-10-30": {
        "open": 12908.56,
        "high": 12958.37,
        "low": 12899.26,
        "close": 12908.66
    },
    "1985-10-31": {
        "open": 12917.02,
        "high": 12953.01,
        "low": 12909.59,
        "close": 12936.47
    }
}
