{
    "1998-09-01": {
        "open": 13979.82,
        "high": 14369.83,
        "low": 13664.74,
        "close": 14369.63
    },
    "1998-09-02": {
        "open": 14361.04,
        "high": 14589.41,
        "low": 14287.16,
        "close": 14376.62
    },
    "1998-09-03": {
        "open": 14362.54,
        "high": 14368.28,
        "low": 14207.84,
        "close": 14261.24
    },
    "1998-09-04": {
        "open": 14158.34,
        "high": 14185.86,
        "low": 14042.91,
        "close": 14042.91
    },
    "1998-09-07": {
        "open": 13984.47,
        "high": 14790.06,
        "low": 13912.69,
        "close": 14790.06
    },
    "1998-09-08": {
        "open": 14766.93,
        "high": 15294.26,
        "low": 14766.93,
        "close": 14913.49
    },
    "1998-09-09": {
        "open": 14968.18,
        "high": 15099.85,
        "low": 14629.62,
        "close": 14755.54
    },
    "1998-09-10": {
        "open": 14805.29,
        "high": 14902,
        "low": 14530.92,
        "close": 14666.03
    },
    "1998-09-11": {
        "open": 14551.25,
        "high": 14551.25,
        "low": 13725.62,
        "close": 13916.98
    },
    "1998-09-14": {
        "open": 13979.32,
        "high": 14329.92,
        "low": 13844.31,
        "close": 14227.37
    },
    "1998-09-16": {
        "open": 14229.32,
        "high": 14375.57,
        "low": 14176.02,
        "close": 14197.7
    },
    "1998-09-17": {
        "open": 14213.49,
        "high": 14279.77,
        "low": 13784.07,
        "close": 13859.14
    },
    "1998-09-18": {
        "open": 13799.75,
        "high": 14006.09,
        "low": 13697.75,
        "close": 13983.12
    },
    "1998-09-21": {
        "open": 13875.77,
        "high": 13875.77,
        "low": 13580.72,
        "close": 13597.3
    },
    "1998-09-22": {
        "open": 13640.56,
        "high": 13871.48,
        "low": 13521.13,
        "close": 13789.81
    },
    "1998-09-24": {
        "open": 13896.79,
        "high": 14297.5,
        "low": 13896.79,
        "close": 14205.78
    },
    "1998-09-25": {
        "open": 14057.85,
        "high": 14057.85,
        "low": 13678.47,
        "close": 13723.84
    },
    "1998-09-28": {
        "open": 13760.74,
        "high": 14121.47,
        "low": 13687.03,
        "close": 13909.37
    },
    "1998-09-29": {
        "open": 13937.82,
        "high": 13952.35,
        "low": 13553.02,
        "close": 13821.43
    },
    "1998-09-30": {
        "open": 13878.68,
        "high": 13966.77,
        "low": 13406.39,
        "close": 13406.39
    }
}
