{
    "2006-04-03": {
        "open": 17127.61,
        "high": 17387.08,
        "low": 17105.5,
        "close": 17333.31
    },
    "2006-04-04": {
        "open": 17295.58,
        "high": 17410.3,
        "low": 17266.39,
        "close": 17292.91
    },
    "2006-04-05": {
        "open": 17340.14,
        "high": 17464.54,
        "low": 17187.35,
        "close": 17243.98
    },
    "2006-04-06": {
        "open": 17365.57,
        "high": 17489.33,
        "low": 17347.01,
        "close": 17489.33
    },
    "2006-04-07": {
        "open": 17498.88,
        "high": 17563.37,
        "low": 17418.94,
        "close": 17563.37
    },
    "2006-04-10": {
        "open": 17455.03,
        "high": 17489.61,
        "low": 17385.25,
        "close": 17456.58
    },
    "2006-04-11": {
        "open": 17460.68,
        "high": 17489.16,
        "low": 17295.42,
        "close": 17418.13
    },
    "2006-04-12": {
        "open": 17297.18,
        "high": 17325.21,
        "low": 17162,
        "close": 17162.55
    },
    "2006-04-13": {
        "open": 17232.28,
        "high": 17303.27,
        "low": 17068.96,
        "close": 17199.15
    },
    "2006-04-14": {
        "open": 17319.33,
        "high": 17319.33,
        "low": 17149.08,
        "close": 17233.82
    },
    "2006-04-17": {
        "open": 17233.73,
        "high": 17233.73,
        "low": 17000.36,
        "close": 17000.36
    },
    "2006-04-18": {
        "open": 16971.76,
        "high": 17268.05,
        "low": 16945.3,
        "close": 17232.86
    },
    "2006-04-19": {
        "open": 17405.92,
        "high": 17459.24,
        "low": 17350.12,
        "close": 17350.12
    },
    "2006-04-20": {
        "open": 17391.94,
        "high": 17412.59,
        "low": 17283.97,
        "close": 17317.53
    },
    "2006-04-21": {
        "open": 17332.35,
        "high": 17479.73,
        "low": 17258.49,
        "close": 17403.96
    },
    "2006-04-24": {
        "open": 17245.62,
        "high": 17245.62,
        "low": 16892.15,
        "close": 16914.4
    },
    "2006-04-25": {
        "open": 16929.36,
        "high": 17000.2,
        "low": 16787.44,
        "close": 16970.29
    },
    "2006-04-26": {
        "open": 16993.23,
        "high": 17107.93,
        "low": 16944.54,
        "close": 17055.93
    },
    "2006-04-27": {
        "open": 17118.92,
        "high": 17176.06,
        "low": 17094.72,
        "close": 17114.54
    },
    "2006-04-28": {
        "open": 17039.37,
        "high": 17043.67,
        "low": 16750.5,
        "close": 16906.23
    }
}
