{
    "2014-04-01": {
        "open": 14870.51,
        "high": 14870.51,
        "low": 14751.29,
        "close": 14791.99
    },
    "2014-04-02": {
        "open": 14897.88,
        "high": 15069.61,
        "low": 14893.17,
        "close": 14946.32
    },
    "2014-04-03": {
        "open": 15009.18,
        "high": 15164.39,
        "low": 14976.36,
        "close": 15071.88
    },
    "2014-04-04": {
        "open": 15005.54,
        "high": 15098.38,
        "low": 15000.69,
        "close": 15063.77
    },
    "2014-04-07": {
        "open": 14880.82,
        "high": 14895.58,
        "low": 14764.37,
        "close": 14808.85
    },
    "2014-04-08": {
        "open": 14715.8,
        "high": 14740.1,
        "low": 14605.31,
        "close": 14606.88
    },
    "2014-04-09": {
        "open": 14436.05,
        "high": 14502.02,
        "low": 14279.34,
        "close": 14299.69
    },
    "2014-04-10": {
        "open": 14484.54,
        "high": 14513.14,
        "low": 14234.45,
        "close": 14300.12
    },
    "2014-04-11": {
        "open": 14027.8,
        "high": 14065.97,
        "low": 13885.11,
        "close": 13960.05
    },
    "2014-04-14": {
        "open": 13887.23,
        "high": 14008.29,
        "low": 13885.22,
        "close": 13910.16
    },
    "2014-04-15": {
        "open": 14068.75,
        "high": 14096.86,
        "low": 13969.17,
        "close": 13996.81
    },
    "2014-04-16": {
        "open": 14126.87,
        "high": 14420.3,
        "low": 14125.59,
        "close": 14417.68
    },
    "2014-04-17": {
        "open": 14395.95,
        "high": 14500.66,
        "low": 14351.85,
        "close": 14417.53
    },
    "2014-04-18": {
        "open": 14489.37,
        "high": 14536.67,
        "low": 14442.74,
        "close": 14516.27
    },
    "2014-04-21": {
        "open": 14549.45,
        "high": 14649.5,
        "low": 14503.17,
        "close": 14512.38
    },
    "2014-04-22": {
        "open": 14586.29,
        "high": 14604.3,
        "low": 14388.77,
        "close": 14388.77
    },
    "2014-04-23": {
        "open": 14480.41,
        "high": 14546.27,
        "low": 14459.29,
        "close": 14546.27
    },
    "2014-04-24": {
        "open": 14563.25,
        "high": 14563.25,
        "low": 14367.13,
        "close": 14404.99
    },
    "2014-04-25": {
        "open": 14369.72,
        "high": 14554.32,
        "low": 14327.6,
        "close": 14429.26
    },
    "2014-04-28": {
        "open": 14289.82,
        "high": 14324.03,
        "low": 14224.47,
        "close": 14288.23
    },
    "2014-04-30": {
        "open": 14393.51,
        "high": 14421.22,
        "low": 14275.69,
        "close": 14304.11
    }
}
